[
  {
    "inputs": [
      {
        "internalType": "string",
        "name": "cid",
        "type": "string"
      }
    ],
    "name": "storeRecord",
    "outputs": [],
    "stateMutability": "nonpayable",
    "type": "function"
  },
  {
    "inputs": [
      {
        "internalType": "string",
        "name": "cid",
        "type": "string"
      }
    ],
    "name": "verify",
    "outputs": [
      {
        "internalType": "bool",
        "name": "",
        "type": "bool"
      }
    ],
    "stateMutability": "view",
    "type": "function"
  }
]